proxy_server.py
proxyanalyzer-1.0.dist-info/METADATA
proxyanalyzer-1.0.dist-info/WHEEL
proxyanalyzer-1.0.dist-info/entry_points.txt
proxyanalyzer-1.0.dist-info/top_level.txt
proxyanalyzer-1.0.dist-info/RECORD
