Metadata-Version: 2.4
Name: ProxyAnalyzer
Version: 1.0
Requires-Dist: mitmproxy
Dynamic: requires-dist
